Workbook
Name Slicer_Price: #N/A

Sheet Worksheet
A1: Name | B1: Author | C1: User Rating | D1: Reviews | E1: Price | F1: Year | G1: Genre | I1: This is the original spreadsheet that we are going to work with, transform and get all the insights we can get after analyzing the data
A2: 10-Day Green Smoothie Cleanse | B2: JJ Smith | C2: 4.7 | D2: 17350 | E2: 105 | F2: 2016 | G2: Non Fiction
A3: 11/22/63: A Novel | B3: Stephen King | C3: 4.6 | D3: 2052 | E3: 105 | F3: 2011 | G3: Fiction
A4: 12 Rules for Life: An Antidote to Chaos | B4: Jordan B. Peterson | C4: 4.7 | D4: 18979 | E4: 82 | F4: 2018 | G4: Non Fiction
A5: 1984 (Signet Classics) | B5: George Orwell | C5: 4.7 | D5: 21424 | E5: 54 | F5: 2017 | G5: Fiction
A6: 5,000 Awesome Facts (About Everything!) (National Geographic Kids) | B6: National Geographic Kids | C6: 4.8 | D6: 7665 | E6: 53 | F6: 2019 | G6: Non Fiction | I6: Tools and functions we are going to use in this exercise: PivotTables, different types of Counts, add/ remove a slicer, some simple visualization chart
A7: A Dance with Dragons (A Song of Ice and Fire) | B7: George R. R. Martin | C7: 4.4 | D7: 12643 | E7: 52 | F7: 2011 | G7: Fiction
A8: A Game of Thrones / A Clash of Kings / A Storm of Swords / A Feast of Crows / A Dance with Dragons | B8: George R. R. Martin | C8: 4.7 | D8: 19735 | E8: 46 | F8: 2014 | G8: Fiction
A9: A Gentleman in Moscow: A Novel | B9: Amor Towles | C9: 4.7 | D9: 19699 | E9: 46 | F9: 2017 | G9: Fiction
A10: A Higher Loyalty: Truth, Lies, and Leadership | B10: James Comey | C10: 4.7 | D10: 5983 | E10: 46 | F10: 2018 | G10: Non Fiction
A11: A Man Called Ove: A Novel | B11: Fredrik Backman | C11: 4.6 | D11: 23848 | E11: 46 | F11: 2016 | G11: Fiction
A12: A Man Called Ove: A Novel | B12: Fredrik Backman | C12: 4.6 | D12: 23848 | E12: 46 | F12: 2017 | G12: Fiction
A13: A Patriot's History of the United States: From Columbus's Great Discovery to the War on Terror | B13: Larry Schweikart | C13: 4.6 | D13: 460 | E13: 46 | F13: 2010 | G13: Non Fiction
A14: A Stolen Life: A Memoir | B14: Jaycee Dugard | C14: 4.6 | D14: 4149 | E14: 46 | F14: 2011 | G14: Non Fiction
A15: A Wrinkle in Time (Time Quintet) | B15: Madeleine L'Engle | C15: 4.5 | D15: 5153 | E15: 46 | F15: 2018 | G15: Fiction
A16: Act Like a Lady, Think Like a Man: What Men Really Think About Love, Relationships, Intimacy, and Commitment | B16: Steve Harvey | C16: 4.6 | D16: 5013 | E16: 46 | F16: 2009 | G16: Non Fiction
A17: Adult Coloring Book Designs: Stress Relief Coloring Book: Garden Designs, Mandalas, Animals, and Paisley Patterns | B17: Adult Coloring Book Designs | C17: 4.5 | D17: 2313 | E17: 46 | F17: 2016 | G17: Non Fiction
A18: Adult Coloring Book: Stress Relieving Animal Designs | B18: Blue Star Coloring | C18: 4.6 | D18: 2925 | E18: 42 | F18: 2015 | G18: Non Fiction
... A551: You Are a Badass: How to Stop Doubting Your Greatness and Start Living an Awesome Life | B551: Jen Sincero | C551: 4.7 | D551: 14331 | E551: 0 | F551: 2019 | G551: Non Fiction

Sheet Pivot Table 1
A1: Name | B1: Sub-total of each book sold | C1: Times purchases made | D1: No of unique prices
A2: Publication Manual of the American Psychological Association, 6th Edition | B2: 110 | C2: =COUNTIF(Worksheet!A:A, A2) -> 10 | D2: =IFERROR(__xludf.DUMMYFUNCTION("COUNTUNIQUE(Worksheet!E2:E551)"),40) -> 40 | F2: In column C we have determined the number of times each book is purchased using the COUNTIFS function
A3: 10-Day Green Smoothie Cleanse | B3: 105 | C3: =COUNTIF(Worksheet!A:A, A3) -> 1
A4: 11/22/63: A Novel | B4: 105 | C4: =COUNTIF(Worksheet!A:A, A4) -> 1
A5: Oh, the Places You'll Go! | B5: 92 | C5: =COUNTIF(Worksheet!A:A, A5) -> 8
A6: A Man Called Ove: A Novel | B6: 92 | C6: =COUNTIF(Worksheet!A:A, A6) -> 2
A7: The 5 Love Languages: The Secret to Love That Lasts | B7: 90 | C7: =COUNTIF(Worksheet!A:A, A7) -> 10
A8: StrengthsFinder 2.0 | B8: 89 | C8: =COUNTIF(Worksheet!A:A, A8) -> 9
A9: First 100 Words | B9: 85 | C9: =COUNTIF(Worksheet!A:A, A9) -> 5 | F9: In column D we have determined all the different rates of the prices of books ranging from 0 to 105, although 0 cannot be considered a price. We calculated this using the COUNTUNIQUE function. We have 40 different rates.
A10: Dear Zoo: A Lift-the-Flap Book | B10: 84 | C10: =COUNTIF(Worksheet!A:A, A10) -> 4
A11: Jesus Calling: Enjoying Peace in His Presence (with Scripture References) | B11: 84 | C11: =COUNTIF(Worksheet!A:A, A11) -> 6
A12: 12 Rules for Life: An Antidote to Chaos | B12: 82 | C12: =COUNTIF(Worksheet!A:A, A12) -> 1
A13: Giraffes Can't Dance | B13: 80 | C13: =COUNTIF(Worksheet!A:A, A13) -> 5
A14: All the Light We Cannot See | B14: 80 | C14: =COUNTIF(Worksheet!A:A, A14) -> 2
A15: Catching Fire (The Hunger Games) | B15: 71 | C15: =COUNTIF(Worksheet!A:A, A15) -> 3
A16: How to Win Friends & Influence People | B16: 70 | C16: =COUNTIF(Worksheet!A:A, A16) -> 5
A17: Crazy Love: Overwhelmed by a Relentless God | B17: 69 | C17: =COUNTIF(Worksheet!A:A, A17) -> 3
A18: Laugh-Out-Loud Jokes for Kids | B18: 65 | C18: =COUNTIF(Worksheet!A:A, A18) -> 5
A19: Good to Great: Why Some Companies Make the Leap and Others Don't | B19: 63 | C19: =COUNTIF(Worksheet!A:A, A19) -> 4
A20: The 7 Habits of Highly Effective People: Powerful Lessons in Personal Change | B20: 63 | C20: =COUNTIF(Worksheet!A:A, A20) -> 7
A21: Becoming | B21: 56 | C21: =COUNTIF(Worksheet!A:A, A21) -> 2
... A351: Wonder | B351: 0 | C351: =COUNTIF(Worksheet!A:A, A351) -> 5
A352: Grand Total | B352: 7205 | C352: =SUM(C2:C351) -> 550

Sheet Pivot Table 2
A1: Genre | B1: Quantities Sold
A2: Fiction | B2: 240 | H2: Genre | I2: Total Amt Sold
A3: Non Fiction | B3: 310 | H3: Fiction | I3: 3093
A4: Grand Total | B4: 550 | H4: Non Fiction | I4: 4112
H5: Grand Total | I5: 7205

Sheet Pivot Table 3
A3: Fiction vs Non-fiction sale in a year | B3: Genre
A4: Year | B4: Fiction | C4: Non Fiction | D4: Grand Total
A5: 2009 | B5: 253 | C5: 356 | D5: 609
A6: 2010 | B6: 202 | C6: 424 | D6: 626
A7: 2011 | B7: 379 | C7: 329 | D7: 708
A8: 2012 | B8: 232 | C8: 288 | D8: 520
A9: 2013 | B9: 318 | C9: 304 | D9: 622
A10: 2014 | B10: 372 | C10: 241 | D10: 613
A11: 2015 | B11: 192 | C11: 571 | D11: 763
A12: 2016 | B12: 256 | C12: 518 | D12: 774
A13: 2017 | B13: 379 | C13: 259 | D13: 638
A14: 2018 | B14: 296 | C14: 436 | D14: 732
A15: 2019 | B15: 214 | C15: 386 | D15: 600
A16: Grand Total | B16: 3093 | C16: 4112 | D16: 7205
